LICENSE.txt
MANIFEST.in
README.rst
setup.py
django_timezone_field_ng.egg-info/PKG-INFO
django_timezone_field_ng.egg-info/SOURCES.txt
django_timezone_field_ng.egg-info/dependency_links.txt
django_timezone_field_ng.egg-info/requires.txt
django_timezone_field_ng.egg-info/top_level.txt
timezone_field/__init__.py
timezone_field/fields.py
timezone_field/forms.py
timezone_field/models.py
timezone_field/utils.py