Metadata-Version: 1.1
Name: django-timezone-field-ng
Version: 2.0
Summary: A Django app providing database and form fields for pytz timezone objects.
Home-page: http://github.com/bgroff/django-timezone-field/
Author: Bryce Groff
Author-email: bgroff@hawaii.edu
License: BSD
Platform: UNKNOWN
Classifier: Development Status :: 5 - Production/Stable
Classifier: Environment :: Web Environment
Classifier: Intended Audience :: Developers
Classifier: License :: OSI Approved :: BSD License
Classifier: Operating System :: OS Independent
Classifier: Programming Language :: Python
Classifier: Programming Language :: Python :: 2
Classifier: Programming Language :: Python :: 2.7
Classifier: Programming Language :: Python :: 3
Classifier: Programming Language :: Python :: 3.4
Classifier: Programming Language :: Python :: 3.5
Classifier: Topic :: Utilities
Classifier: Framework :: Django
